{"ts": "2026-07-24T13:04:18+00:00", "total_active": 746, "routes": [{"route": "1", "active": 27, "stopped": 15, "in_transit": 12}, {"route": "2", "active": 31, "stopped": 11, "in_transit": 20}, {"route": "3", "active": 22, "stopped": 6, "in_transit": 16}, {"route": "4", "active": 27, "stopped": 12, "in_transit": 15}, {"route": "5", "active": 28, "stopped": 11, "in_transit": 17}, {"route": "6", "active": 24, "stopped": 14, "in_transit": 10}, {"route": "6X", "active": 5, "stopped": 1, "in_transit": 4}, {"route": "7", "active": 26, "stopped": 9, "in_transit": 17}, {"route": "7X", "active": 6, "stopped": 5, "in_transit": 1}, {"route": "A", "active": 46, "stopped": 29, "in_transit": 17}, {"route": "B", "active": 34, "stopped": 23, "in_transit": 11}, {"route": "C", "active": 28, "stopped": 15, "in_transit": 13}, {"route": "D", "active": 41, "stopped": 25, "in_transit": 16}, {"route": "E", "active": 43, "stopped": 21, "in_transit": 22}, {"route": "F", "active": 54, "stopped": 35, "in_transit": 19}, {"route": "FS", "active": 30, "stopped": 18, "in_transit": 12}, {"route": "G", "active": 24, "stopped": 10, "in_transit": 14}, {"route": "H", "active": 17, "stopped": 10, "in_transit": 7}, {"route": "J", "active": 32, "stopped": 17, "in_transit": 15}, {"route": "L", "active": 23, "stopped": 11, "in_transit": 12}, {"route": "M", "active": 36, "stopped": 20, "in_transit": 16}, {"route": "N", "active": 32, "stopped": 17, "in_transit": 15}, {"route": "Q", "active": 36, "stopped": 21, "in_transit": 15}, {"route": "R", "active": 42, "stopped": 27, "in_transit": 15}, {"route": "SI", "active": 8, "stopped": 4, "in_transit": 4}, {"route": "W", "active": 24, "stopped": 11, "in_transit": 13}]}