{"ts": "2026-07-17T18:16:35+00:00", "total_active": 663, "routes": [{"route": "1", "active": 21, "stopped": 10, "in_transit": 11}, {"route": "2", "active": 25, "stopped": 8, "in_transit": 17}, {"route": "3", "active": 16, "stopped": 10, "in_transit": 6}, {"route": "4", "active": 20, "stopped": 6, "in_transit": 14}, {"route": "5", "active": 23, "stopped": 14, "in_transit": 9}, {"route": "6", "active": 27, "stopped": 14, "in_transit": 13}, {"route": "7", "active": 23, "stopped": 17, "in_transit": 6}, {"route": "7X", "active": 1, "stopped": 1, "in_transit": 0}, {"route": "A", "active": 37, "stopped": 21, "in_transit": 16}, {"route": "B", "active": 35, "stopped": 20, "in_transit": 15}, {"route": "C", "active": 32, "stopped": 17, "in_transit": 15}, {"route": "D", "active": 39, "stopped": 24, "in_transit": 15}, {"route": "E", "active": 34, "stopped": 15, "in_transit": 19}, {"route": "F", "active": 47, "stopped": 29, "in_transit": 18}, {"route": "FS", "active": 18, "stopped": 6, "in_transit": 12}, {"route": "G", "active": 24, "stopped": 10, "in_transit": 14}, {"route": "GS", "active": 1, "stopped": 1, "in_transit": 0}, {"route": "H", "active": 20, "stopped": 12, "in_transit": 8}, {"route": "J", "active": 24, "stopped": 12, "in_transit": 12}, {"route": "L", "active": 18, "stopped": 14, "in_transit": 4}, {"route": "M", "active": 37, "stopped": 21, "in_transit": 16}, {"route": "N", "active": 34, "stopped": 20, "in_transit": 14}, {"route": "Q", "active": 33, "stopped": 19, "in_transit": 14}, {"route": "R", "active": 43, "stopped": 26, "in_transit": 17}, {"route": "SI", "active": 8, "stopped": 3, "in_transit": 5}, {"route": "W", "active": 23, "stopped": 10, "in_transit": 13}]}